README.md
setup.py
xj_python/__init__.py
xj_python/xj_python.py
xj_python/xj_python_bak.py
xj_python.egg-info/PKG-INFO
xj_python.egg-info/SOURCES.txt
xj_python.egg-info/dependency_links.txt
xj_python.egg-info/requires.txt
xj_python.egg-info/top_level.txt