Metadata-Version: 1.0
Name: xj-python
Version: 0.11
Summary: xj system
Home-page: https://github.com/karaage0703/xj_python
Author: karaage0703
Author-email: UNKNOWN
License: MIT
Platform: UNKNOWN
